{
  "_fv": 13,
  "_type": "recipe",
  "definition": {
    "recipeType": "Crafting",
    "xpReward": 0.0,
    "cookingTime": 200,
    "recipeRetstackSize": 1,
    "group": "",
    "recipeShapeless": true,
    "recipeSlots": [
      {
        "value": ""
      },
      {
        "value": "CUSTOM:ClothesArmor.boots"
      },
      {
        "value": ""
      },
      {
        "value": ""
      },
      {
        "value": "CUSTOM:ShockAbsorberAArmor.boots"
      },
      {
        "value": ""
      },
      {
        "value": ""
      },
      {
        "value": "Items.IRON_BOOTS"
      },
      {
        "value": ""
      }
    ],
    "recipeReturnStack": {
      "value": "CUSTOM:AntiShockArmor.boots"
    },
    "name": "anti_shock_boots_recipe",
    "namespace": "mod"
  }
}